./.gitignore
./PKG-INFO
./README.md
./__init__.py
./pyproject.toml
./hiagent_eva/__init__.py
./hiagent_eva/client.py
hiagent_eva-2.4.0.dist-info/METADATA
hiagent_eva-2.4.0.dist-info/WHEEL
hiagent_eva-2.4.0.dist-info/RECORD
