Metadata-Version: 2.4
Name: hiagent-eva
Version: 2.4.0
Summary: HiAgent Eva SDK
Requires-Python: >=3.10
Requires-Dist: hiagent-api>=2.3.0
Requires-Dist: python-dotenv>=1.1.0
Requires-Dist: requests>=2.32.3
Requires-Dist: tenacity>=9.1.2
